Metadata-Version: 2.1
Name: mailru-im-bot_dorokhin
Version: 0.0.23
Summary: Pure Python interface for Bot API. Bot cookbook for Humans.
Author-email: "ICQ LLC (Mail.Ru Group)" <support@icq.com>
Project-URL: Homepage, https://github.com/dorokhin/bot-python
Classifier: Intended Audience :: Developers
Classifier: Topic :: Software Development :: Libraries :: Python Modules
Classifier: Topic :: Communications :: Chat
Classifier: Topic :: Internet
Classifier: Programming Language :: Python :: 3.10
Classifier: Programming Language :: Python :: 3.11
Classifier: Programming Language :: Python :: 3.12
Classifier: Operating System :: OS Independent
Requires-Python: >=3.10
License-File: LICENSE
Requires-Dist: cached-property ==1.5.2
Requires-Dist: certifi ==2023.11.17
Requires-Dist: click ==8.1.7
Requires-Dist: expiringdict ==1.2.2
Requires-Dist: gtts ==2.5.0
Requires-Dist: idna ==3.6
Requires-Dist: python-baseconv ==1.2.2
Requires-Dist: requests ==2.31.0
Requires-Dist: six ==1.16.0
Requires-Dist: urllib3 ==2.1.0
